<?xml version="1.0" encoding="UTF-8" ?>
<NotepadPlus>
    <Session activeView="0">
        <mainView activeIndex="3">
            <File firstVisibleLine="0" xOffset="0" scrollWidth="49" startPos="6" endPos="6" selMode="0" offset="0" wrapCount="1" lang="None (Normal Text)" encoding="-1" userReadOnly="no" filename="Z:\home\decimal\index.html.txt" backupFilePath="" originalFileLastModifTimestamp="480502610" originalFileLastModifTimestampHigh="30937957" mapFirstVisibleDisplayLine="-1" mapFirstVisibleDocLine="-1" mapLastVisibleDocLine="-1" mapNbLine="-1" mapHigherPos="-1" mapWidth="-1" mapHeight="-1" mapKByteInDoc="0" mapWrapIndentMode="-1" mapIsWrap="no" />
            <File firstVisibleLine="0" xOffset="0" scrollWidth="347" startPos="151" endPos="151" selMode="0" offset="0" wrapCount="1" lang="None (Normal Text)" encoding="-1" userReadOnly="no" filename="Z:\home\decimal\Dikshant\setting.html.txt" backupFilePath="C:\users\decimal\Application Data\Notepad++\backup\setting.html.txt@2022-01-27_153738" originalFileLastModifTimestamp="0" originalFileLastModifTimestampHigh="0" mapFirstVisibleDisplayLine="-1" mapFirstVisibleDocLine="-1" mapLastVisibleDocLine="-1" mapNbLine="-1" mapHigherPos="-1" mapWidth="-1" mapHeight="-1" mapKByteInDoc="66144" mapWrapIndentMode="-1" mapIsWrap="no" />
            <File firstVisibleLine="0" xOffset="0" scrollWidth="14" startPos="3" endPos="3" selMode="0" offset="0" wrapCount="1" lang="None (Normal Text)" encoding="-1" userReadOnly="no" filename="Z:\home\decimal\Dikshant\abhi.html.txt" backupFilePath="" originalFileLastModifTimestamp="0" originalFileLastModifTimestampHigh="0" mapFirstVisibleDisplayLine="-1" mapFirstVisibleDocLine="-1" mapLastVisibleDocLine="-1" mapNbLine="-1" mapHigherPos="-1" mapWidth="-1" mapHeight="-1" mapKByteInDoc="106" mapWrapIndentMode="-1" mapIsWrap="no" />
            <File firstVisibleLine="0" xOffset="0" scrollWidth="27" startPos="4" endPos="4" selMode="0" offset="0" wrapCount="1" lang="None (Normal Text)" encoding="-1" userReadOnly="no" filename="new 1" backupFilePath="C:\users\decimal\Application Data\Notepad++\backup\new 1@2022-01-28_003320" originalFileLastModifTimestamp="0" originalFileLastModifTimestampHigh="0" mapFirstVisibleDisplayLine="-1" mapFirstVisibleDocLine="-1" mapLastVisibleDocLine="-1" mapNbLine="-1" mapHigherPos="-1" mapWidth="-1" mapHeight="-1" mapKByteInDoc="6816837" mapWrapIndentMode="-1" mapIsWrap="no" />
        </mainView>
        <subView activeIndex="0" />
    </Session>
</NotepadPlus>
